tests/__init__.py
tests/test_addressable.py
tests/test_elements.py
tests/test_route.py
weconnect/__init__.py
weconnect/__version.py
weconnect/addressable.py
weconnect/domain.py
weconnect/errors.py
weconnect/util.py
weconnect/weconnect.py
weconnect/weconnect_errors.py
weconnect/auth/__init__.py
weconnect/auth/auth_util.py
weconnect/auth/my_cupra_session.py
weconnect/auth/openid_session.py
weconnect/auth/session_manager.py
weconnect/auth/vw_web_session.py
weconnect/auth/we_charge_session.py
weconnect/auth/we_connect_session.py
weconnect/badges/charging.png
weconnect/badges/connected.png
weconnect/badges/cooling.png
weconnect/badges/heating.png
weconnect/badges/locked.png
weconnect/badges/parking.png
weconnect/badges/unlocked.png
weconnect/badges/ventilating.png
weconnect/badges/warning.png
weconnect/elements/__init__.py
weconnect/elements/access_status.py
weconnect/elements/activeventilation_timer.py
weconnect/elements/auxiliaryheating_status.py
weconnect/elements/auxiliaryheating_timer.py
weconnect/elements/battery_status.py
weconnect/elements/battery_support_status.py
weconnect/elements/capability_status.py
weconnect/elements/charge_mode.py
weconnect/elements/charging_care_settings.py
weconnect/elements/charging_profiles.py
weconnect/elements/charging_settings.py
weconnect/elements/charging_station.py
weconnect/elements/charging_status.py
weconnect/elements/climatization_settings.py
weconnect/elements/climatization_status.py
weconnect/elements/climatization_timer.py
weconnect/elements/control_operation.py
weconnect/elements/controls.py
weconnect/elements/departure_timers_status.py
weconnect/elements/enums.py
weconnect/elements/error.py
weconnect/elements/fuel_level_status.py
weconnect/elements/general_controls.py
weconnect/elements/generic_capability.py
weconnect/elements/generic_request_status.py
weconnect/elements/generic_settings.py
weconnect/elements/generic_status.py
weconnect/elements/lights_status.py
weconnect/elements/lv_battery_status.py
weconnect_darkfox_dev-0.0.9.dist-info/LICENSE
weconnect_darkfox_dev-0.0.9.dist-info/METADATA
weconnect_darkfox_dev-0.0.9.dist-info/WHEEL
weconnect_darkfox_dev-0.0.9.dist-info/top_level.txt
weconnect_darkfox_dev-0.0.9.dist-info/RECORD
